coiled/__init__.py
coiled/__main__.py
coiled/analytics.py
coiled/auth.py
coiled/batch.py
coiled/capture_environment.py
coiled/cluster.py
coiled/coiled.yaml
coiled/compatibility.py
coiled/config.py
coiled/context.py
coiled/core.py
coiled/errors.py
coiled/exceptions.py
coiled/filestore.py
coiled/function.py
coiled/plugins.py
coiled/prefect.py
coiled/pypi_conda_map.py
coiled/scan.py
coiled/software.py
coiled/software_utils.py
coiled/spans.py
coiled/spark.py
coiled/types.py
coiled/utils.py
coiled/websockets.py
coiled/cli/__init__.py
coiled/cli/config.py
coiled/cli/core.py
coiled/cli/curl.py
coiled/cli/diagnostics.py
coiled/cli/env.py
coiled/cli/file.py
coiled/cli/login.py
coiled/cli/mpi.py
coiled/cli/package_sync.py
coiled/cli/prefect.py
coiled/cli/prefect_serve.py
coiled/cli/run.py
coiled/cli/sync.py
coiled/cli/utils.py
coiled/cli/batch/__init__.py
coiled/cli/batch/list.py
coiled/cli/batch/logs.py
coiled/cli/batch/run.py
coiled/cli/batch/status.py
coiled/cli/batch/util.py
coiled/cli/batch/wait.py
coiled/cli/cluster/__init__.py
coiled/cli/cluster/azure_logs.py
coiled/cli/cluster/better_logs.py
coiled/cli/cluster/crud.py
coiled/cli/cluster/get_address.py
coiled/cli/cluster/list.py
coiled/cli/cluster/logs.py
coiled/cli/cluster/metrics.py
coiled/cli/cluster/ssh.py
coiled/cli/cluster/utils.py
coiled/cli/hello/__init__.py
coiled/cli/hello/hello.py
coiled/cli/hello/utils.py
coiled/cli/hello/examples/__init__.py
coiled/cli/hello/examples/exit.py
coiled/cli/hello/examples/hello_world.py
coiled/cli/hello/examples/nyc_parquet.py
coiled/cli/hello/examples/pytorch.py
coiled/cli/hello/examples/xarray_nwm.py
coiled/cli/hello/scripts/fill_ipython.py
coiled/cli/hello/scripts/nyc_parquet.py
coiled/cli/hello/scripts/pytorch.py
coiled/cli/hello/scripts/xarray_nwm.py
coiled/cli/notebook/__init__.py
coiled/cli/notebook/notebook.py
coiled/cli/setup/__init__.py
coiled/cli/setup/amp.py
coiled/cli/setup/aws.py
coiled/cli/setup/azure.py
coiled/cli/setup/entry.py
coiled/cli/setup/gcp.py
coiled-1.130.4.dist-info/METADATA
coiled-1.130.4.dist-info/WHEEL
coiled-1.130.4.dist-info/entry_points.txt
coiled-1.130.4.dist-info/licenses/LICENSE
coiled-1.130.4.dist-info/RECORD
